crossref/__init__.py
crossref/argument_checkers.py
crossref/argument_parsers.py
crossref/command_handlers.py
crossref/crossref_cli.py
crossref/utils.py
crossref-0.1.2.dist-info/METADATA
crossref-0.1.2.dist-info/WHEEL
crossref-0.1.2.dist-info/entry_points.txt
crossref-0.1.2.dist-info/top_level.txt
crossref-0.1.2.dist-info/RECORD
