Metadata-Version: 2.1
Name: crossref
Version: 0.1.2
Summary: "A Python wrapper for the Crossref API"
Home-page: https://github.com/TralahM/academic_citations
Author: TralahM
Author-email: briantralah@gmail.com
License: MIT
